CHANGES.rst
LICENSE
MANIFEST.in
README.rst
requirements.txt
setup.cfg
setup.py
tox.ini
netvisor/__init__.py
netvisor/_compat.py
netvisor/auth.py
netvisor/client.py
netvisor/core.py
netvisor/exc.py
netvisor.egg-info/PKG-INFO
netvisor.egg-info/SOURCES.txt
netvisor.egg-info/dependency_links.txt
netvisor.egg-info/pbr.json
netvisor.egg-info/requires.txt
netvisor.egg-info/top_level.txt
netvisor/requests/__init__.py
netvisor/requests/accounting.py
netvisor/requests/base.py
netvisor/requests/company.py
netvisor/requests/customer.py
netvisor/requests/product.py
netvisor/requests/sales_invoice.py
netvisor/requests/sales_payment.py
netvisor/responses/__init__.py
netvisor/responses/accounting.py
netvisor/responses/base.py
netvisor/responses/companies.py
netvisor/responses/customers.py
netvisor/responses/products.py
netvisor/responses/sales_invoices.py
netvisor/responses/sales_payments.py
netvisor/schemas/__init__.py
netvisor/schemas/common.py
netvisor/schemas/fields.py
netvisor/schemas/replies.py
netvisor/schemas/accounting/__init__.py
netvisor/schemas/accounting/list.py
netvisor/schemas/companies/__init__.py
netvisor/schemas/companies/get.py
netvisor/schemas/companies/list.py
netvisor/schemas/customers/__init__.py
netvisor/schemas/customers/create.py
netvisor/schemas/customers/get.py
netvisor/schemas/customers/list.py
netvisor/schemas/products/__init__.py
netvisor/schemas/products/get.py
netvisor/schemas/products/list.py
netvisor/schemas/sales_invoices/__init__.py
netvisor/schemas/sales_invoices/create.py
netvisor/schemas/sales_invoices/get.py
netvisor/schemas/sales_invoices/list.py
netvisor/schemas/sales_payments/__init__.py
netvisor/schemas/sales_payments/list.py
netvisor/services/__init__.py
netvisor/services/accounting.py
netvisor/services/base.py
netvisor/services/company.py
netvisor/services/customer.py
netvisor/services/product.py
netvisor/services/sales_invoice.py
netvisor/services/sales_payment.py
tests/__init__.py
tests/test_auth.py
tests/utils.py
tests/data/requests/CrmProcess.xml
tests/data/requests/Customer.xml
tests/data/requests/CustomerMinimal.xml
tests/data/requests/Product.xml
tests/data/requests/SalesInvoice.xml
