Metadata-Version: 1.1
Name: netvisor
Version: 0.7.0
Summary: Python wrapper for the Netvisor API
Home-page: http://github.com/fastmonkeys/netvisor.py
Author: Janne Vanhala
Author-email: janne@fastmonkeys.com
License: The MIT License (MIT)
